<?xml version="1.0" encoding="UTF-8"?>
<lido:lido xmlns:gml="http://www.opengis.net/gml" xmlns:lido="http://www.lido-schema.org" xmlns:xlink="http://www.w3.org/1999/xlink">
  <lido:lidoRecID lido:type="global" lido:source="Museum voor Schone Kunsten Gent" lido:label="dataPID">http://mskgent.be/collection/work/data/S-15</lido:lidoRecID>
  <lido:objectPublishedID lido:type="global" lido:source="Museum voor Schone Kunsten Gent" lido:label="workPID">http://mskgent.be/collection/work/id/S-15</lido:objectPublishedID>
  <lido:descriptiveMetadata>
    <lido:objectClassificationWrap>
      <lido:objectWorkTypeWrap>
        <lido:objectWorkType>
          <lido:term lido:pref="preferred" xml:lang="nl">schilderingen</lido:term>
        </lido:objectWorkType>
      </lido:objectWorkTypeWrap>
      <lido:classificationWrap>
        <lido:classification>
          <lido:conceptID lido:pref="alternate" lido:type="global" lido:source="AAT">http://vocab.getty.edu/aat/300033799</lido:conceptID>
          <lido:term lido:pref="alternate">olieverfschilderingen</lido:term>
          <lido:term lido:pref="preferred">olieverfschilderij</lido:term>
        </lido:classification>
      </lido:classificationWrap>
    </lido:objectClassificationWrap>
    <lido:objectIdentificationWrap>
      <lido:titleWrap>
        <lido:titleSet>
          <lido:appellationValue xml:lang="nl">Johannes schrijft zijn Openbaring op het eiland Patmos</lido:appellationValue>
        </lido:titleSet>
      </lido:titleWrap>
      <lido:objectDescriptionWrap>
        <lido:objectDescriptionSet>
          <lido:descriptiveNoteValue xml:lang="nl">In Johannes op Patmos, afkomstig uit het stadhuis in Gent, herkennen we de apostel en lievelingsleerling van Christus, Johannes. De attributen waarmee hij vaak wordt afgebeeld, de arend en de pen, tonen hem als schrijver van het laatste en meest spirituele van de vier evangelies. Na de hemelvaart van Christus vestigde Johannes  zich in Efeze. Omwille van zijn actieve rol in de verspreiding van het christendom werd hij vervolgd en uiteindelijk naar het eiland Patmos verbannen. Daar schreef hij zijn Openbaringen of Apocalyps, een profetisch boek waarin het schrikwekkende einde van de mensheid in hallucinante beelden wordt opgeroepen. Het visionaire moment van inspiratie is door Gaspar de Crayer vrij dramatisch voorgesteld, wat typisch is voor het late werk van de meester. De man die model stond voor de figuur van Johannes, vinden we terug bij Rubens in de triptiek voor het graf van Jan Michielsen in de kathedraal van Antwerpen.</lido:descriptiveNoteValue>
        </lido:objectDescriptionSet>
        <lido:objectDescriptionSet>
          <lido:descriptiveNoteValue xml:lang="en"/>
        </lido:objectDescriptionSet>
      </lido:objectDescriptionWrap>
      <lido:objectMeasurementsWrap>
        <lido:objectMeasurementsSet>
          <lido:objectMeasurements>
            <lido:measurementsSet>
              <lido:measurementType>hoogte</lido:measurementType>
              <lido:measurementUnit>cm</lido:measurementUnit>
              <lido:measurementValue>129.4</lido:measurementValue>
            </lido:measurementsSet>
          </lido:objectMeasurements>
        </lido:objectMeasurementsSet>
        <lido:objectMeasurementsSet>
          <lido:objectMeasurements>
            <lido:measurementsSet>
              <lido:measurementType>breedte</lido:measurementType>
              <lido:measurementUnit>cm</lido:measurementUnit>
              <lido:measurementValue>100.6</lido:measurementValue>
            </lido:measurementsSet>
          </lido:objectMeasurements>
        </lido:objectMeasurementsSet>
      </lido:objectMeasurementsWrap>
    </lido:objectIdentificationWrap>
    <lido:eventWrap>
      <lido:eventSet>
        <lido:event>
          <lido:eventType>
            <lido:term>Production</lido:term>
          </lido:eventType>
          <lido:eventActor>
            <lido:actorInRole>
              <lido:actor>
                <lido:actorID lido:type="local" lido:source="Adlib">310000039</lido:actorID>
                <lido:actorID lido:type="url" lido:source="VIAF">http://viaf.org/viaf/76588643</lido:actorID>
                <lido:actorID lido:type="url" lido:source="RKD">http://explore.rkd.nl/nl/explore/artists/19021</lido:actorID>
                <lido:actorID lido:type="url" lido:source="Wikidata">http://www.wikidata.org/wiki/Q570172</lido:actorID>
                <lido:nameActorSet>
                  <lido:appellationValue lido:pref="alternate">Crayer, Gaspar de</lido:appellationValue>
                  <lido:appellationValue lido:pref="preferred">Gaspar de Crayer</lido:appellationValue>
                </lido:nameActorSet>
                <lido:vitalDatesActor>
                  <lido:earliestDate>1584</lido:earliestDate>
                  <lido:latestDate>1669</lido:latestDate>
                </lido:vitalDatesActor>
              </lido:actor>
            </lido:actorInRole>
          </lido:eventActor>
          <lido:eventDate>
            <lido:displayDate>circa 1649 - 1669</lido:displayDate>
            <lido:date>
              <lido:earliestDate lido:type="circa">1649</lido:earliestDate>
              <lido:latestDate lido:type="circa">1669</lido:latestDate>
            </lido:date>
          </lido:eventDate>
          <lido:periodName>
            <lido:term xml:lang="nl">17de eeuw</lido:term>
          </lido:periodName>
          <lido:eventPlace>
            <lido:place>
              <lido:namePlaceSet>
                <lido:appellationValue lido:pref="preferred" xml:lang="nl"/>
              </lido:namePlaceSet>
            </lido:place>
          </lido:eventPlace>
          <lido:eventMaterialsTech>
            <lido:materialsTech>
              <lido:termMaterialsTech lido:type="physicalDescription"/>
            </lido:materialsTech>
          </lido:eventMaterialsTech>
        </lido:event>
      </lido:eventSet>
    </lido:eventWrap>
    <lido:objectRelationWrap>
      <lido:subjectWrap>
        <lido:subjectSet>
          <lido:subject>
            <lido:subjectConcept>
              <lido:term xml:lang="nl">religieuze voorstellingen</lido:term>
            </lido:subjectConcept>
          </lido:subject>
        </lido:subjectSet>
      </lido:subjectWrap>
    </lido:objectRelationWrap>
  </lido:descriptiveMetadata>
  <lido:administrativeMetadata>
    <lido:recordWrap>
      <lido:recordID lido:type="local">S-15</lido:recordID>
      <lido:recordID lido:type="Adlib">310004898</lido:recordID>
      <lido:recordType>
        <lido:conceptID lido:type="local" lido:source="AAT">http://vocab.getty.edu/aat/300133025</lido:conceptID>
        <lido:term>Item</lido:term>
      </lido:recordType>
      <lido:recordSource>
        <lido:legalBodyName>
          <lido:appellationValue>Museum voor Schone Kunsten Gent</lido:appellationValue>
        </lido:legalBodyName>
        <lido:legalBodyWeblink>http://mskgent.be</lido:legalBodyWeblink>
      </lido:recordSource>
    </lido:recordWrap>
  </lido:administrativeMetadata>
</lido:lido>
